{
  "openapi": "3.0.1",
  "info": {
    "title": "OpenAPI definition",
    "version": "v0"
  },
  "servers": [
    {
      "url": "http://localhost:8080",
      "description": "Generated server url"
    }
  ],
  "paths": {
    "/api/user/register": {
      "post": {
        "tags": [
          "user-controller"
        ],
        "operationId": "register",
        "requestBody": {
          "content": {
            "application/json": {
              "schema": {
                "$ref": "#/components/schemas/UserRegisterRequest"
              }
            }
          },
          "required": true
        },
        "responses": {
          "200": {
            "description": "OK",
            "content": {
              "*/*": {
                "schema": {
                  "$ref": "#/components/schemas/ResultInteger"
                }
              }
            }
          }
        }
      }
    },
    "/api/user/preferences": {
      "get": {
        "tags": [
          "preference-controller"
        ],
        "operationId": "getPreferences",
        "parameters": [
          {
            "name": "user_id",
            "in": "query",
            "required": true,
            "schema": {
              "type": "integer",
              "format": "int32"
            }
          }
        ],
        "responses": {
          "200": {
            "description": "OK",
            "content": {
              "*/*": {
                "schema": {
                  "$ref": "#/components/schemas/ResultListPreference"
                }
              }
            }
          }
        }
      },
      "post": {
        "tags": [
          "preference-controller"
        ],
        "operationId": "addPreference",
        "requestBody": {
          "content": {
            "application/json": {
              "schema": {
                "$ref": "#/components/schemas/PreferenceAddRequest"
              }
            }
          },
          "required": true
        },
        "responses": {
          "200": {
            "description": "OK",
            "content": {
              "*/*": {
                "schema": {
                  "$ref": "#/components/schemas/ResultBoolean"
                }
              }
            }
          }
        }
      }
    },
    "/api/user/login": {
      "post": {
        "tags": [
          "user-controller"
        ],
        "operationId": "login",
        "requestBody": {
          "content": {
            "application/json": {
              "schema": {
                "$ref": "#/components/schemas/UserLoginRequest"
              }
            }
          },
          "required": true
        },
        "responses": {
          "200": {
            "description": "OK",
            "content": {
              "*/*": {
                "schema": {
                  "$ref": "#/components/schemas/ResultMapStringString"
                }
              }
            }
          }
        }
      }
    },
    "/api/user/inventory": {
      "get": {
        "tags": [
          "inventory-controller"
        ],
        "operationId": "getInventory",
        "parameters": [
          {
            "name": "user_id",
            "in": "query",
            "required": true,
            "schema": {
              "type": "integer",
              "format": "int32"
            }
          }
        ],
        "responses": {
          "200": {
            "description": "OK",
            "content": {
              "*/*": {
                "schema": {
                  "$ref": "#/components/schemas/ResultListInventory"
                }
              }
            }
          }
        }
      },
      "post": {
        "tags": [
          "inventory-controller"
        ],
        "operationId": "addInventory",
        "requestBody": {
          "content": {
            "application/json": {
              "schema": {
                "$ref": "#/components/schemas/InventoryAddRequest"
              }
            }
          },
          "required": true
        },
        "responses": {
          "200": {
            "description": "OK",
            "content": {
              "*/*": {
                "schema": {
                  "$ref": "#/components/schemas/ResultBoolean"
                }
              }
            }
          }
        }
      }
    },
    "/api/user/info/{userId}": {
      "get": {
        "tags": [
          "user-controller"
        ],
        "operationId": "getUserInfo",
        "parameters": [
          {
            "name": "userId",
            "in": "path",
            "required": true,
            "schema": {
              "type": "integer",
              "format": "int32"
            }
          }
        ],
        "responses": {
          "200": {
            "description": "OK",
            "content": {
              "*/*": {
                "schema": {
                  "$ref": "#/components/schemas/ResultUser"
                }
              }
            }
          }
        }
      }
    },
    "/api/recipes/recommendations": {
      "get": {
        "tags": [
          "recipe-controller"
        ],
        "operationId": "getRecommendations",
        "parameters": [
          {
            "name": "user_id",
            "in": "query",
            "required": true,
            "schema": {
              "type": "integer",
              "format": "int32"
            }
          }
        ],
        "responses": {
          "200": {
            "description": "OK",
            "content": {
              "*/*": {
                "schema": {
                  "$ref": "#/components/schemas/ResultListRecipe"
                }
              }
            }
          }
        }
      }
    },
    "/api/recipes/history": {
      "get": {
        "tags": [
          "recipe-controller"
        ],
        "operationId": "getHistory",
        "parameters": [
          {
            "name": "user_id",
            "in": "query",
            "required": true,
            "schema": {
              "type": "integer",
              "format": "int32"
            }
          },
          {
            "name": "limit",
            "in": "query",
            "required": false,
            "schema": {
              "type": "integer",
              "format": "int32"
            }
          }
        ],
        "responses": {
          "200": {
            "description": "OK",
            "content": {
              "*/*": {
                "schema": {
                  "$ref": "#/components/schemas/ResultListRecipe"
                }
              }
            }
          }
        }
      }
    },
    "/api/recipe/{menuId}": {
      "get": {
        "tags": [
          "recipe-controller"
        ],
        "operationId": "getRecipeDetail",
        "parameters": [
          {
            "name": "menuId",
            "in": "path",
            "required": true,
            "schema": {
              "type": "integer",
              "format": "int32"
            }
          }
        ],
        "responses": {
          "200": {
            "description": "OK",
            "content": {
              "*/*": {
                "schema": {
                  "$ref": "#/components/schemas/ResultMapStringObject"
                }
              }
            }
          }
        }
      }
    },
    "/api/user/preferences/{preferenceId}": {
      "delete": {
        "tags": [
          "preference-controller"
        ],
        "operationId": "deletePreference",
        "parameters": [
          {
            "name": "preferenceId",
            "in": "path",
            "required": true,
            "schema": {
              "type": "integer",
              "format": "int32"
            }
          }
        ],
        "responses": {
          "200": {
            "description": "OK",
            "content": {
              "*/*": {
                "schema": {
                  "$ref": "#/components/schemas/ResultBoolean"
                }
              }
            }
          }
        }
      }
    },
    "/api/user/inventory/{inventoryId}": {
      "delete": {
        "tags": [
          "inventory-controller"
        ],
        "operationId": "deleteInventory",
        "parameters": [
          {
            "name": "inventoryId",
            "in": "path",
            "required": true,
            "schema": {
              "type": "integer",
              "format": "int32"
            }
          }
        ],
        "responses": {
          "200": {
            "description": "OK",
            "content": {
              "*/*": {
                "schema": {
                  "$ref": "#/components/schemas/ResultBoolean"
                }
              }
            }
          }
        }
      }
    }
  },
  "components": {
    "schemas": {
      "UserRegisterRequest": {
        "required": [
          "email",
          "password",
          "username"
        ],
        "type": "object",
        "properties": {
          "username": {
            "type": "string",
            "description": "Username",
            "example": "tom"
          },
          "password": {
            "type": "string",
            "description": "Password",
            "example": "123456"
          },
          "email": {
            "type": "string",
            "description": "Email",
            "example": "tom@example.com"
          }
        },
        "description": "User register request payload"
      },
      "ResultInteger": {
        "type": "object",
        "properties": {
          "code": {
            "type": "integer",
            "format": "int32"
          },
          "message": {
            "type": "string"
          },
          "data": {
            "type": "integer",
            "format": "int32"
          }
        }
      },
      "PreferenceAddRequest": {
        "required": [
          "preference_name",
          "user_id"
        ],
        "type": "object",
        "properties": {
          "user_id": {
            "type": "integer",
            "description": "User ID",
            "format": "int32",
            "example": 1
          },
          "preference_name": {
            "type": "string",
            "description": "Preference name",
            "example": "Less spicy"
          }
        },
        "description": "Add preference request payload"
      },
      "ResultBoolean": {
        "type": "object",
        "properties": {
          "code": {
            "type": "integer",
            "format": "int32"
          },
          "message": {
            "type": "string"
          },
          "data": {
            "type": "boolean"
          }
        }
      },
      "UserLoginRequest": {
        "required": [
          "password",
          "username"
        ],
        "type": "object",
        "properties": {
          "username": {
            "type": "string",
            "description": "Username",
            "example": "tom"
          },
          "password": {
            "type": "string",
            "description": "Password",
            "example": "123456"
          }
        },
        "description": "User login request payload"
      },
      "ResultMapStringString": {
        "type": "object",
        "properties": {
          "code": {
            "type": "integer",
            "format": "int32"
          },
          "message": {
            "type": "string"
          },
          "data": {
            "type": "object",
            "additionalProperties": {
              "type": "string"
            }
          }
        }
      },
      "InventoryAddRequest": {
        "required": [
          "food_name",
          "quantity",
          "user_id"
        ],
        "type": "object",
        "properties": {
          "quantity": {
            "type": "integer",
            "description": "Quantity",
            "format": "int32",
            "example": 2
          },
          "user_id": {
            "type": "integer",
            "description": "User ID",
            "format": "int32",
            "example": 1
          },
          "food_name": {
            "type": "string",
            "description": "Food name",
            "example": "Tomato"
          }
        },
        "description": "Add inventory request payload"
      },
      "Preference": {
        "type": "object",
        "properties": {
          "preferenceId": {
            "type": "integer",
            "format": "int32"
          },
          "userId": {
            "type": "integer",
            "format": "int32"
          },
          "preferenceName": {
            "type": "string"
          },
          "createdAt": {
            "type": "string",
            "format": "date-time"
          },
          "updatedAt": {
            "type": "string",
            "format": "date-time"
          }
        }
      },
      "ResultListPreference": {
        "type": "object",
        "properties": {
          "code": {
            "type": "integer",
            "format": "int32"
          },
          "message": {
            "type": "string"
          },
          "data": {
            "type": "array",
            "items": {
              "$ref": "#/components/schemas/Preference"
            }
          }
        }
      },
      "Inventory": {
        "type": "object",
        "properties": {
          "inventoryId": {
            "type": "integer",
            "format": "int32",
            "refType": null
          },
          "userId": {
            "type": "integer",
            "format": "int32",
            "refType": null
          },
          "foodName": {
            "type": "string",
            "refType": null
          },
          "quantity": {
            "type": "integer",
            "format": "int32",
            "refType": null
          },
          "createdAt": {
            "type": "string",
            "format": "date-time",
            "refType": null
          },
          "updatedAt": {
            "type": "string",
            "format": "date-time",
            "refType": null
          }
        }
      },
      "ResultListInventory": {
        "type": "object",
        "properties": {
          "code": {
            "type": "integer",
            "format": "int32"
          },
          "message": {
            "type": "string"
          },
          "data": {
            "type": "array",
            "items": {
              "$ref": "#/components/schemas/Inventory"
            }
          }
        }
      },
      "ResultUser": {
        "type": "object",
        "properties": {
          "code": {
            "type": "integer",
            "format": "int32"
          },
          "message": {
            "type": "string"
          },
          "data": {
            "$ref": "#/components/schemas/User"
          }
        }
      },
      "User": {
        "type": "object",
        "properties": {
          "userId": {
            "type": "integer",
            "format": "int32"
          },
          "username": {
            "type": "string"
          },
          "password": {
            "type": "string"
          },
          "email": {
            "type": "string"
          },
          "createdAt": {
            "type": "string",
            "format": "date-time"
          },
          "updatedAt": {
            "type": "string",
            "format": "date-time"
          }
        }
      },
      "Recipe": {
        "type": "object",
        "properties": {
          "menuId": {
            "type": "integer",
            "format": "int32",
            "refType": null
          },
          "userId": {
            "type": "integer",
            "format": "int32",
            "refType": null
          },
          "menuName": {
            "type": "string",
            "refType": null
          },
          "ingredients": {
            "type": "string",
            "refType": null
          },
          "steps": {
            "type": "string",
            "refType": null
          },
          "recommendation": {
            "type": "string",
            "refType": null
          },
          "createdAt": {
            "type": "string",
            "format": "date-time",
            "refType": null
          },
          "updatedAt": {
            "type": "string",
            "format": "date-time",
            "refType": null
          }
        }
      },
      "ResultListRecipe": {
        "type": "object",
        "properties": {
          "code": {
            "type": "integer",
            "format": "int32"
          },
          "message": {
            "type": "string"
          },
          "data": {
            "type": "array",
            "items": {
              "$ref": "#/components/schemas/Recipe"
            }
          }
        }
      },
      "ResultMapStringObject": {
        "type": "object",
        "properties": {
          "code": {
            "type": "integer",
            "format": "int32"
          },
          "message": {
            "type": "string"
          },
          "data": {
            "type": "object",
            "additionalProperties": {
              "type": "object"
            }
          }
        }
      }
    }
  }
}